{
  "parent": "minecraft:block/block",
  "textures": {
    "front": "manufactory:block/grinder_side",
    "side": "manufactory:block/grinder_side",
    "inside": "manufactory:block/grinder_inside",
    "back": "manufactory:block/grinder_back_socket",
    "top": "manufactory:block/grinder_top",
    "bottom": "minecraft:block/furnace_top",
    "particle": "manufactory:block/grinder_side"
  },
  "elements": [
    {
      "from": [
        2,
        0,
        0
      ],
      "to": [
        14,
        16,
        2
      ],
      "faces": {
        "down": {
          "texture": "#bottom"
        },
        "up": {
          "texture": "#top"
        },
        "north": {
          "texture": "#side"
        },
        "south": {
          "texture": "#inside"
        }
      }
    },
    {
      "from": [
        14,
        0,
        0
      ],
      "to": [
        16,
        16,
        16
      ],
      "faces": {
        "down": {
          "texture": "#bottom"
        },
        "up": {
          "texture": "#top"
        },
        "north": {
          "texture": "#side"
        },
        "south": {
          "texture": "#back"
        },
        "west": {
          "texture": "#inside"
        },
        "east": {
          "texture": "#side"
        }
      }
    },
    {
      "from": [
        2,
        0,
        14
      ],
      "to": [
        14,
        16,
        16
      ],
      "faces": {
        "down": {
          "texture": "#bottom"
        },
        "up": {
          "texture": "#top"
        },
        "north": {
          "texture": "#inside"
        },
        "south": {
          "texture": "#back"
        }
      }
    },
    {
      "from": [
        0,
        0,
        0
      ],
      "to": [
        2,
        16,
        16
      ],
      "faces": {
        "down": {
          "texture": "#bottom"
        },
        "up": {
          "texture": "#top"
        },
        "north": {
          "texture": "#side"
        },
        "south": {
          "texture": "#back"
        },
        "west": {
          "texture": "#side"
        },
        "east": {
          "texture": "#inside"
        }
      }
    },
    {
      "from": [
        2,
        0,
        2
      ],
      "to": [
        14,
        2,
        14
      ],
      "faces": {
        "down": {
          "texture": "#bottom"
        },
        "up": {
          "texture": "#bottom"
        }
      }
    }
  ]
}