{
  "parent": "minecraft:recipes/root",
  "rewards": {
    "recipes": [
      "manufactory:ground_gold_ore_rough_from_nether_gold_ore"
    ]
  },
  "criteria": {
    "has_nether_gold_ore": {
      "trigger": "minecraft:inventory_changed",
      "conditions": {
        "items": [
          {
            "items": [
              "minecraft:nether_gold_ore"
            ]
          }
        ]
      }
    },
    "has_the_recipe": {
      "trigger": "minecraft:recipe_unlocked",
      "conditions": {
        "recipe": "manufactory:ground_gold_ore_rough_from_nether_gold_ore"
      }
    }
  },
  "requirements": [
    [
      "has_nether_gold_ore",
      "has_the_recipe"
    ]
  ]
}